vcf_to_dict.py
rimetools-0.0.1.dist-info/LICENSE
rimetools-0.0.1.dist-info/METADATA
rimetools-0.0.1.dist-info/WHEEL
rimetools-0.0.1.dist-info/entry_points.txt
rimetools-0.0.1.dist-info/top_level.txt
rimetools-0.0.1.dist-info/RECORD
