Metadata-Version: 2.1
Name: rimetools
Version: 0.0.1
Summary: rime输入法相关工具
Home-page: https://github.com/whitewatercn/rimetool
Author: whitewatercn
Author-email: whitewatercn@outlook.com
Project-URL: Bug Reports, https://github.com/whitewatercn/rimetool/issues
Project-URL: Say Thanks!, http://xlog.whitewater.wang
Project-URL: Source, https://github.com/whitewatercn/rimetool
Keywords: rime input method editor tool
Classifier: Development Status :: 3 - Alpha
Classifier: Intended Audience :: Developers
Classifier: Topic :: Software Development :: Build Tools
Classifier: License :: OSI Approved :: MIT License
Classifier: Programming Language :: Python :: 2
Classifier: Programming Language :: Python :: 2.7
Classifier: Programming Language :: Python :: 3
Classifier: Programming Language :: Python :: 3.4
Classifier: Programming Language :: Python :: 3.5
Classifier: Programming Language :: Python :: 3.6
Classifier: Programming Language :: Python :: 3.7
Classifier: Programming Language :: Python :: 3.8
Classifier: Programming Language :: Python :: 3.9
Classifier: Programming Language :: Python :: 3.10
License-File: LICENSE
Requires-Dist: pypinyin
Requires-Dist: argparse
